pyfindlib/__init__.py
pyfindlib/__main__.py
pyfindlib/action.py
pyfindlib/alg.py
pyfindlib/cli.py
pyfindlib/executor.py
pyfindlib/lib.py
pyfindlib/node.py
pyfindlib/parse.py
pyfindlib/predicate.py
pyfindlib/shared.py
pyfindlib/tok.py
pyfindlib/types.py
pyfindlib-0.0.5.dist-info/LICENSE
pyfindlib-0.0.5.dist-info/METADATA
pyfindlib-0.0.5.dist-info/WHEEL
pyfindlib-0.0.5.dist-info/entry_points.txt
pyfindlib-0.0.5.dist-info/top_level.txt
pyfindlib-0.0.5.dist-info/RECORD
