Metadata-Version: 2.2
Name: pyfindlib
Version: 0.0.5
Summary: Shell utility resembling findutils, small, extendable and windows-friendly
Home-page: https://github.com/mugiseyebrows/pyfindlib
Author: Stanislav Doronin
Author-email: mugisbrows@gmail.com
License-File: LICENSE
Requires-Dist: python-dateutil
Requires-Dist: bashrange
Requires-Dist: shortwalk
Dynamic: author
Dynamic: author-email
Dynamic: description
Dynamic: description-content-type
Dynamic: home-page
Dynamic: requires-dist
Dynamic: summary
